pydecidim/__init__.py
pydecidim/api/__init__.py
pydecidim/api/abstract_decidim_reader.py
pydecidim/api/comment_reader.py
pydecidim/api/decidim_connector.py
pydecidim/api/participatory_process_reader.py
pydecidim/api/participatory_processes_reader.py
pydecidim/api/participatory_space_name_enum.py
pydecidim/api/participatory_space_reader.py
pydecidim/api/participatory_spaces_reader.py
pydecidim/api/proposal_comment_reader.py
pydecidim/api/proposal_reader.py
pydecidim/api/proposals_reader.py
pydecidim/api/version_reader.py
pydecidim/model/CommentTreeElement.py
pydecidim/model/__init__.py
pydecidim/model/abstract_api_element.py
pydecidim/model/author.py
pydecidim/model/comment.py
pydecidim/model/component_filter.py
pydecidim/model/component_interface.py
pydecidim/model/component_sort.py
pydecidim/model/elemental_type_element.py
pydecidim/model/participatory_process.py
pydecidim/model/participatory_process_filter.py
pydecidim/model/participatory_process_sort.py
pydecidim/model/proposal.py
pydecidim/model/translated_field.py
pydecidim/tests/__init__.py
pydecidim/tests/test_comment_reader.py
pydecidim/tests/test_decidim_connector.py
pydecidim/tests/test_participatory_process_reader.py
pydecidim/tests/test_participatory_processes_reader.py
pydecidim/tests/test_proposal_reader.py
pydecidim/tests/test_proposals_reader.py
pydecidim/tests/test_translated_field.py
pydecidim/tests/test_version_reader.py
pydecidim-0.1.2.dist-info/LICENSE.txt
pydecidim-0.1.2.dist-info/METADATA
pydecidim-0.1.2.dist-info/WHEEL
pydecidim-0.1.2.dist-info/top_level.txt
pydecidim-0.1.2.dist-info/RECORD
